setup.py
pullword/__init__.py
pullword/pullword.py
pullword.egg-info/PKG-INFO
pullword.egg-info/SOURCES.txt
pullword.egg-info/dependency_links.txt
pullword.egg-info/requires.txt
pullword.egg-info/top_level.txt