Metadata-Version: 1.0
Name: pullword
Version: 0.0.1
Summary: the sdk for pullword.com -- a free online Chinese text segmentation platform
Home-page: UNKNOWN
Author: binhe22
Author-email: UNKNOWN
License: MIT License
Keywords: pullword
Platform: any
